odoo/addons/l10n_es_aeat_mod130/README.rst
odoo/addons/l10n_es_aeat_mod130/__init__.py
odoo/addons/l10n_es_aeat_mod130/__manifest__.py
odoo/addons/l10n_es_aeat_mod130/data/aeat_export_mod130_data.xml
odoo/addons/l10n_es_aeat_mod130/doc/DR130e15v11.xls
odoo/addons/l10n_es_aeat_mod130/i18n/bg.po
odoo/addons/l10n_es_aeat_mod130/i18n/ca.po
odoo/addons/l10n_es_aeat_mod130/i18n/ca_ES.po
odoo/addons/l10n_es_aeat_mod130/i18n/cs.po
odoo/addons/l10n_es_aeat_mod130/i18n/en_US.po
odoo/addons/l10n_es_aeat_mod130/i18n/es.po
odoo/addons/l10n_es_aeat_mod130/i18n/es_CO.po
odoo/addons/l10n_es_aeat_mod130/i18n/es_CR.po
odoo/addons/l10n_es_aeat_mod130/i18n/eu.po
odoo/addons/l10n_es_aeat_mod130/i18n/fr.po
odoo/addons/l10n_es_aeat_mod130/i18n/gl.po
odoo/addons/l10n_es_aeat_mod130/i18n/hr.po
odoo/addons/l10n_es_aeat_mod130/i18n/l10n_es_aeat_mod130.pot
odoo/addons/l10n_es_aeat_mod130/i18n/nl.po
odoo/addons/l10n_es_aeat_mod130/i18n/pl.po
odoo/addons/l10n_es_aeat_mod130/i18n/pt.po
odoo/addons/l10n_es_aeat_mod130/i18n/pt_BR.po
odoo/addons/l10n_es_aeat_mod130/i18n/ru.po
odoo/addons/l10n_es_aeat_mod130/i18n/sl.po
odoo/addons/l10n_es_aeat_mod130/i18n/sv.po
odoo/addons/l10n_es_aeat_mod130/i18n/tr.po
odoo/addons/l10n_es_aeat_mod130/i18n/vi.po
odoo/addons/l10n_es_aeat_mod130/models/__init__.py
odoo/addons/l10n_es_aeat_mod130/models/mod130.py
odoo/addons/l10n_es_aeat_mod130/readme/CONTRIBUTORS.rst
odoo/addons/l10n_es_aeat_mod130/readme/DESCRIPTION.rst
odoo/addons/l10n_es_aeat_mod130/readme/ROADMAP.rst
odoo/addons/l10n_es_aeat_mod130/security/ir.model.access.csv
odoo/addons/l10n_es_aeat_mod130/security/ir_rule.xml
odoo/addons/l10n_es_aeat_mod130/static/description/icon.png
odoo/addons/l10n_es_aeat_mod130/static/description/icon_source.svg
odoo/addons/l10n_es_aeat_mod130/static/description/index.html
odoo/addons/l10n_es_aeat_mod130/tests/__init__.py
odoo/addons/l10n_es_aeat_mod130/tests/test_l10n_es_aeat_mod130.py
odoo/addons/l10n_es_aeat_mod130/views/mod130_view.xml
odoo12_addon_l10n_es_aeat_mod130-12.0.1.3.1.dist-info/METADATA
odoo12_addon_l10n_es_aeat_mod130-12.0.1.3.1.dist-info/WHEEL
odoo12_addon_l10n_es_aeat_mod130-12.0.1.3.1.dist-info/top_level.txt
odoo12_addon_l10n_es_aeat_mod130-12.0.1.3.1.dist-info/RECORD
